CHANGELOG.rst
MANIFEST.in
README.rst
buildout.cfg
setup.py
src/collective/__init__.py
src/collective.downloadtracker.egg-info/PKG-INFO
src/collective.downloadtracker.egg-info/SOURCES.txt
src/collective.downloadtracker.egg-info/dependency_links.txt
src/collective.downloadtracker.egg-info/entry_points.txt
src/collective.downloadtracker.egg-info/namespace_packages.txt
src/collective.downloadtracker.egg-info/not-zip-safe
src/collective.downloadtracker.egg-info/requires.txt
src/collective.downloadtracker.egg-info/top_level.txt
src/collective/downloadtracker/__init__.py
src/collective/downloadtracker/configure.zcml
src/collective/downloadtracker/download_patch.py
src/collective/downloadtracker/extender.py
src/collective/downloadtracker/interfaces.py
src/collective/downloadtracker/testing.py
src/collective/downloadtracker/browser/__init__.py
src/collective/downloadtracker/browser/configure.zcml
src/collective/downloadtracker/browser/delete.py
src/collective/downloadtracker/browser/download_records.pt
src/collective/downloadtracker/browser/dt.js
src/collective/downloadtracker/browser/interfaces.py
src/collective/downloadtracker/browser/viewlets.py
src/collective/downloadtracker/profiles/default/browserlayer.xml
src/collective/downloadtracker/profiles/default/jsregistry.xml
src/collective/downloadtracker/profiles/default/skins.xml
src/collective/downloadtracker/profiles/default/viewlets.xml
src/collective/downloadtracker/profiles/uninstall/browserlayer.xml
src/collective/downloadtracker/profiles/uninstall/jsregistry.xml
src/collective/downloadtracker/profiles/uninstall/skins.xml
src/collective/downloadtracker/profiles/uninstall/viewlets.xml
src/collective/downloadtracker/skins/downloadtracker/at_download.py
src/collective/downloadtracker/tests/__init__.py
src/collective/downloadtracker/tests/image.jpg
src/collective/downloadtracker/tests/test_setup.py