Metadata-Version: 1.1
Name: collective.downloadtracker
Version: 1.0a4
Summary: It tracks which registered user has downloaded a file (ATFile) at which time. It displays this value in aviewlet below File's title. Administrators are able to delete tracked records.
Home-page: http://pypi.python.org/pypi/collective.downloadtracker
Author: Pavel Bogdanović
Author-email: pb@prontonet.eu
License: BSD
Keywords: plone zope
Platform: UNKNOWN
Classifier: Framework :: Plone
Classifier: Programming Language :: Python
